{"generated_at":"2026-05-18T22:32:38.439038+00:00","vehicles":[{"r":"99","lat":49.2669,"lon":-123.24157,"b":null},{"r":"99","lat":49.26382,"lon":-123.20821,"b":null},{"r":"25","lat":49.2508,"lon":-123.18513,"b":null},{"r":"99","lat":49.2638,"lon":-123.2069,"b":null},{"r":"R4","lat":49.23462,"lon":-123.1575,"b":null},{"r":"99","lat":49.26375,"lon":-123.15258,"b":null},{"r":"84","lat":49.26843,"lon":-123.16938,"b":null},{"r":"R4","lat":49.23257,"lon":-123.06883,"b":null},{"r":"25","lat":49.24405,"lon":-123.06303,"b":null},{"r":"R4","lat":49.2337,"lon":-123.12231,"b":null},{"r":"99","lat":49.2627,"lon":-123.09634,"b":null},{"r":"33","lat":49.25825,"lon":-123.2118,"b":null},{"r":"25","lat":49.24992,"lon":-123.18446,"b":null},{"r":"25","lat":49.24912,"lon":-123.01002,"b":null},{"r":"25","lat":49.2486,"lon":-123.056,"b":null},{"r":"25","lat":49.24915,"lon":-123.11996,"b":null},{"r":"25","lat":49.26773,"lon":-123.24842,"b":null},{"r":"R4","lat":49.238,"lon":-123.03046,"b":null},{"r":"R4","lat":49.2382,"lon":-123.03101,"b":null},{"r":"R4","lat":49.24453,"lon":-123.23275,"b":null},{"r":"R4","lat":49.23478,"lon":-123.19605,"b":null},{"r":"49","lat":49.24598,"lon":-123.23273,"b":null},{"r":"49","lat":49.22725,"lon":-123.16472,"b":null},{"r":"49","lat":49.22707,"lon":-123.14643,"b":null},{"r":"49","lat":49.22547,"lon":-123.08992,"b":null},{"r":"49","lat":49.2248,"lon":-123.04162,"b":null},{"r":"49","lat":49.22538,"lon":-123.07796,"b":null},{"r":"49","lat":49.22673,"lon":-123.13288,"b":null},{"r":"49","lat":49.22728,"lon":-123.16405,"b":null},{"r":"49","lat":49.22232,"lon":-122.99718,"b":null},{"r":"84","lat":49.26878,"lon":-123.22508,"b":null},{"r":"99","lat":49.26295,"lon":-123.06789,"b":null},{"r":"99","lat":49.26323,"lon":-123.11408,"b":null},{"r":"33","lat":49.258,"lon":-123.18467,"b":null},{"r":"33","lat":49.24012,"lon":-123.06955,"b":null},{"r":"99","lat":49.26333,"lon":-123.11643,"b":null},{"r":"25","lat":49.25482,"lon":-123.0045,"b":null},{"r":"R4","lat":49.23318,"lon":-123.10205,"b":null},{"r":"33","lat":49.24298,"lon":-123.10915,"b":null},{"r":"99","lat":49.26368,"lon":-123.14467,"b":null},{"r":"49","lat":49.24413,"lon":-123.23245,"b":null},{"r":"49","lat":49.25507,"lon":-123.23575,"b":null},{"r":"25","lat":49.2663,"lon":-123.00155,"b":null},{"r":"68","lat":49.2519,"lon":-123.23521,"b":null},{"r":"49","lat":49.22462,"lon":-123.03187,"b":null},{"r":"68","lat":49.27255,"lon":-123.25155,"b":null},{"r":"68","lat":49.26842,"lon":-123.24767,"b":null},{"r":"25","lat":49.26727,"lon":-123.24776,"b":null},{"r":"99","lat":49.26845,"lon":-123.24718,"b":null},{"r":"84","lat":49.26673,"lon":-123.09012,"b":null},{"r":"R4","lat":49.23467,"lon":-123.16092,"b":null},{"r":"R4","lat":49.26068,"lon":-123.24075,"b":null},{"r":"99","lat":49.26325,"lon":-123.12022,"b":null},{"r":"25","lat":49.24893,"lon":-123.11675,"b":null},{"r":"99","lat":49.26287,"lon":-123.09893,"b":null}],"alerts":[{"routes":["R4"],"header":"Stop 60386 Eastbound W 41 Ave @ East Blvd is temporarily closed beginning Monday May 4. Please use new stop 60548 near Maple St.","desc":"","effect":"NO_EFFECT"},{"routes":["49"],"header":"Stop 51987 Eastbound E 49 Ave @ Elliott St is temporarily closed from Tue May 12 through Fri May 22 due to construction. 430 bus will be picking up passengers at the next stop #51988 EB 49 Ave and Vivian St.","desc":"","effect":"REDUCED_SERVICE"},{"routes":["49"],"header":"Stop 52047 Westbound W 49 Ave @ Larch St is temporarily closed until end of service on May 20 due to construction.","desc":"","effect":"REDUCED_SERVICE"},{"routes":["49"],"header":"Stop 60732 Westbound 49 Ave @ Main St is closed beginning Monday May 18. Please use original stop 52030 on other side of Main St.","desc":"","effect":"NO_EFFECT"},{"routes":["49"],"header":"49 Metrotown Station trip leaving UBC Exchange @ Bay 5 at 2:32 pm is cancelled today from 49 Ave and Quebec St due to traffic.","desc":"","effect":"NO_SERVICE"}]}