{"generated_at":"2026-06-19T23:09:43.811706+00:00","vehicles":[{"r":"44","lat":49.28655,"lon":-123.1177,"b":null},{"r":"44","lat":49.27923,"lon":-123.12908,"b":null},{"r":"25","lat":49.25013,"lon":-123.1726,"b":null},{"r":"R4","lat":49.23435,"lon":-123.13808,"b":null},{"r":"R4","lat":49.23415,"lon":-123.13415,"b":null},{"r":"99","lat":49.26522,"lon":-123.21588,"b":null},{"r":"R4","lat":49.23482,"lon":-123.18182,"b":null},{"r":"R4","lat":49.23478,"lon":-123.17398,"b":null},{"r":"25","lat":49.2559,"lon":-123.18513,"b":null},{"r":"99","lat":49.26408,"lon":-123.16713,"b":null},{"r":"44","lat":49.2686,"lon":-123.19185,"b":null},{"r":"99","lat":49.26385,"lon":-123.20783,"b":null},{"r":"R4","lat":49.2346,"lon":-123.15688,"b":null},{"r":"84","lat":49.26827,"lon":-123.16463,"b":null},{"r":"33","lat":49.24957,"lon":-123.11545,"b":null},{"r":"33","lat":49.24858,"lon":-123.11567,"b":null},{"r":"99","lat":49.26372,"lon":-123.14954,"b":null},{"r":"99","lat":49.26703,"lon":-123.24017,"b":null},{"r":"44","lat":49.26857,"lon":-123.1783,"b":null},{"r":"33","lat":49.24058,"lon":-123.0535,"b":null},{"r":"R4","lat":49.23275,"lon":-123.06625,"b":null},{"r":"R4","lat":49.23288,"lon":-123.0844,"b":null},{"r":"R4","lat":49.23298,"lon":-123.09137,"b":null},{"r":"49","lat":49.23155,"lon":-123.18542,"b":null},{"r":"R4","lat":49.23382,"lon":-123.12688,"b":null},{"r":"99","lat":49.26243,"lon":-123.0893,"b":null},{"r":"99","lat":49.26245,"lon":-123.09323,"b":null},{"r":"99","lat":49.2636,"lon":-123.13468,"b":null},{"r":"99","lat":49.26352,"lon":-123.12605,"b":null},{"r":"R4","lat":49.2328,"lon":-123.05608,"b":null},{"r":"R4","lat":49.23333,"lon":-123.03678,"b":null},{"r":"R4","lat":49.23327,"lon":-123.03695,"b":null},{"r":"49","lat":49.22717,"lon":-123.00671,"b":null},{"r":"R4","lat":49.23305,"lon":-123.0419,"b":null},{"r":"R4","lat":49.23285,"lon":-123.05572,"b":null},{"r":"25","lat":49.24568,"lon":-123.06603,"b":null},{"r":"25","lat":49.2638,"lon":-123.24347,"b":null},{"r":"25","lat":49.24802,"lon":-123.16448,"b":null},{"r":"25","lat":49.24917,"lon":-123.1283,"b":null},{"r":"25","lat":49.24903,"lon":-123.12207,"b":null},{"r":"25","lat":49.24842,"lon":-123.07236,"b":null},{"r":"25","lat":49.24843,"lon":-123.07545,"b":null},{"r":"25","lat":49.24845,"lon":-123.07265,"b":null},{"r":"25","lat":49.24817,"lon":-123.00835,"b":null},{"r":"25","lat":49.24335,"lon":-123.05679,"b":null},{"r":"25","lat":49.24928,"lon":-123.1253,"b":null},{"r":"25","lat":49.24817,"lon":-123.16485,"b":null},{"r":"33","lat":49.2584,"lon":-123.21005,"b":null},{"r":"33","lat":49.26823,"lon":-123.24809,"b":null},{"r":"49","lat":49.2677,"lon":-123.24772,"b":null},{"r":"49","lat":49.2689,"lon":-123.24813,"b":null},{"r":"R4","lat":49.23853,"lon":-123.03249,"b":null},{"r":"R4","lat":49.23622,"lon":-123.0338,"b":null},{"r":"R4","lat":49.23813,"lon":-123.03077,"b":null},{"r":"R4","lat":49.23822,"lon":-123.031,"b":null},{"r":"R4","lat":49.23795,"lon":-123.0312,"b":null},{"r":"R4","lat":49.23928,"lon":-123.21682,"b":null},{"r":"R4","lat":49.25008,"lon":-123.24308,"b":null},{"r":"R4","lat":49.23482,"lon":-123.19607,"b":null},{"r":"49","lat":49.23908,"lon":-123.21358,"b":null},{"r":"44","lat":49.2688,"lon":-123.24775,"b":null},{"r":"84","lat":49.2683,"lon":-123.24813,"b":null},{"r":"84","lat":49.27343,"lon":-123.24583,"b":null},{"r":"49","lat":49.22732,"lon":-123.16441,"b":null},{"r":"49","lat":49.22537,"lon":-123.084,"b":null},{"r":"49","lat":49.22665,"lon":-123.13116,"b":null},{"r":"49","lat":49.22513,"lon":-123.06107,"b":null},{"r":"49","lat":49.22477,"lon":-123.0467,"b":null},{"r":"49","lat":49.22472,"lon":-123.04156,"b":null},{"r":"49","lat":49.2264,"lon":-123.00882,"b":null},{"r":"49","lat":49.22488,"lon":-123.05548,"b":null},{"r":"49","lat":49.22553,"lon":-123.09151,"b":null},{"r":"49","lat":49.2262,"lon":-123.11622,"b":null},{"r":"49","lat":49.2272,"lon":-123.15505,"b":null},{"r":"49","lat":49.22978,"lon":-123.17764,"b":null},{"r":"49","lat":49.22263,"lon":-122.99727,"b":null},{"r":"44","lat":49.27127,"lon":-123.23085,"b":null},{"r":"49","lat":49.22198,"lon":-123.01875,"b":null},{"r":"99","lat":49.26322,"lon":-123.06857,"b":null},{"r":"99","lat":49.26287,"lon":-123.06775,"b":null},{"r":"99","lat":49.26232,"lon":-123.07612,"b":null},{"r":"44","lat":49.28627,"lon":-123.1184,"b":null},{"r":"99","lat":49.26427,"lon":-123.18063,"b":null},{"r":"84","lat":49.26617,"lon":-123.0807,"b":null},{"r":"68","lat":49.25862,"lon":-123.25452,"b":null},{"r":"68","lat":49.25763,"lon":-123.24998,"b":null},{"r":"99","lat":49.26283,"lon":-123.09724,"b":null},{"r":"25","lat":49.25712,"lon":-123.23237,"b":null},{"r":"33","lat":49.256,"lon":-123.23521,"b":null},{"r":"R4","lat":49.26147,"lon":-123.24126,"b":null},{"r":"33","lat":49.23987,"lon":-123.06485,"b":null},{"r":"33","lat":49.25722,"lon":-123.14687,"b":null},{"r":"33","lat":49.25732,"lon":-123.15473,"b":null},{"r":"99","lat":49.26333,"lon":-123.11645,"b":null},{"r":"33","lat":49.24518,"lon":-123.11322,"b":null},{"r":"99","lat":49.26435,"lon":-123.18465,"b":null},{"r":"99","lat":49.26415,"lon":-123.17085,"b":null},{"r":"25","lat":49.26623,"lon":-123.0019,"b":null},{"r":"25","lat":49.25447,"lon":-123.00449,"b":null},{"r":"99","lat":49.26302,"lon":-123.1071,"b":null},{"r":"99","lat":49.26405,"lon":-123.16425,"b":null},{"r":"44","lat":49.27653,"lon":-123.13365,"b":null},{"r":"49","lat":49.25763,"lon":-123.23811,"b":null},{"r":"49","lat":49.22588,"lon":-123.10915,"b":null},{"r":"99","lat":49.26242,"lon":-123.06872,"b":null},{"r":"49","lat":49.22483,"lon":-123.05115,"b":null},{"r":"99","lat":49.26363,"lon":-123.14127,"b":null},{"r":"99","lat":49.26362,"lon":-123.14162,"b":null},{"r":"99","lat":49.26383,"lon":-123.15456,"b":null},{"r":"49","lat":49.24757,"lon":-123.2318,"b":null},{"r":"49","lat":49.2392,"lon":-123.21619,"b":null},{"r":"49","lat":49.25645,"lon":-123.23685,"b":null},{"r":"84","lat":49.26772,"lon":-123.098,"b":null},{"r":"25","lat":49.26625,"lon":-123.0011,"b":null},{"r":"68","lat":49.25443,"lon":-123.23515,"b":null},{"r":"99","lat":49.26747,"lon":-123.24686,"b":null},{"r":"99","lat":49.26657,"lon":-123.24565,"b":null},{"r":"25","lat":49.24318,"lon":-123.0612,"b":null},{"r":"R4","lat":49.23265,"lon":-123.07788,"b":null},{"r":"R4","lat":49.23282,"lon":-123.091,"b":null},{"r":"R4","lat":49.23265,"lon":-123.07735,"b":null},{"r":"R4","lat":49.26695,"lon":-123.24602,"b":null},{"r":"R4","lat":49.2672,"lon":-123.24773,"b":null},{"r":"R4","lat":49.26858,"lon":-123.18076,"b":null},{"r":"25","lat":49.2667,"lon":-123.24583,"b":null},{"r":"84","lat":49.26842,"lon":-123.1114,"b":null},{"r":"49","lat":49.22633,"lon":-123.00457,"b":null},{"r":"49","lat":49.22612,"lon":-123.00412,"b":null},{"r":"99","lat":49.26857,"lon":-123.24812,"b":null},{"r":"99","lat":49.26828,"lon":-123.24809,"b":null},{"r":"99","lat":49.26647,"lon":-123.24543,"b":null},{"r":"R4","lat":49.23472,"lon":-123.17212,"b":null},{"r":"R4","lat":49.23433,"lon":-123.14022,"b":null},{"r":"R4","lat":49.23458,"lon":-123.15826,"b":null},{"r":"R4","lat":49.23462,"lon":-123.15617,"b":null},{"r":"R4","lat":49.23465,"lon":-123.15475,"b":null},{"r":"99","lat":49.26327,"lon":-123.12078,"b":null},{"r":"99","lat":49.26347,"lon":-123.12479,"b":null},{"r":"99","lat":49.26348,"lon":-123.12746,"b":null},{"r":"99","lat":49.26347,"lon":-123.12818,"b":null},{"r":"99","lat":49.26352,"lon":-123.13007,"b":null},{"r":"84","lat":49.26842,"lon":-123.16792,"b":null},{"r":"84","lat":49.26602,"lon":-123.12403,"b":null},{"r":"99","lat":49.26332,"lon":-123.11578,"b":null},{"r":"99","lat":49.26322,"lon":-123.11179,"b":null},{"r":"49","lat":49.2261,"lon":-123.1173,"b":null},{"r":"99","lat":49.26285,"lon":-123.09779,"b":null}],"alerts":[{"routes":["49"],"header":"Stop 51969 Eastbound W 49 Ave @ Manitoba St  is back in service beginning Mon, Jun 1.","desc":"","effect":"NO_EFFECT"},{"routes":["49"],"header":"Stop Westbound W 49 Ave @ Cambie St is closed beginning Mon, Jun 1. Please use new stop 61218 Langara-49th Station @ Bay 2, on other side of Cambie St.","desc":"","effect":"NO_EFFECT"},{"routes":["49"],"header":"Stop 62043 Westbound E 49 Ave @ Quebec St is temporarily closed beginning Mon, Jun 1.","desc":"","effect":"NO_EFFECT"},{"routes":["N17"],"header":"Update - extended: Stop 50602 Westbound University Blvd @ 5100 Block is temporarily closed from Fri Jun 5 through Fri Jun 26 due to construction.","desc":"","effect":"REDUCED_SERVICE"},{"routes":["49"],"header":"Stop 51987 Eastbound E 49 Ave @ Elliott St has temporarily moved west to Clarendon St, from Mon Jun 8 at 7:00 AM to Mon Jun 22 at 3:00 PM, due to construction.","desc":"","effect":"STOP_MOVED"},{"routes":["49"],"header":"The following Eastbound stops for Bus 49 Metrotown  are closed beginning Monday June 8.","desc":"Stop 51890 Eastbound W 41 Avenue @ Highbury Street is closed beginning Monday June 8.\r\nStop 51944 Southbound Dunbar Street @ W 43 Avenue is closed beginning Monday June 8.\r\nStop 51952 Eastbound W 49 Avenue @ Balsam Street is closed beginning Monday June 8.\r\nStop 51955 Eastbound W 49 Avenue @ East Blvd Street is closed beginning Monday June 8.\r\nStop 51957 Eastbound W 49 Avenue @ Angus Drive is clos","effect":"NO_EFFECT"},{"routes":["33"],"header":"Stop 51817 Eastbound E 29 Ave @ Slocan St is temporarily closed beginning Monday June 8.","desc":"","effect":"NO_EFFECT"},{"routes":["49"],"header":"The following stops for bus 49 Westbound are closed beginning Monday June 8.","desc":"Stop 51894 Westbound W 41 Avenue @ Olympic Street is closed beginning Monday June 8.\r\nStop 52054 Northbound Dunbar Street @  W 43 Avenue is closed beginning Monday June 8.\r\nStop 52042 Westbound W 49 Avenue @ Adera Street is closed beginning Monday June 8.\r\nStop 52024 Westbound E 49 Avenue @ Ross Street is closed beginning Monday June 8.\r\nStop 52019 Westbound E 49 Avenue @ Beatrice Street is closed","effect":"NO_EFFECT"},{"routes":["49"],"header":"Stop 59768 Eastbound W 49 Avenue @ Wiltshire Street is back in service beginning Monday June 8.","desc":"","effect":"NO_EFFECT"},{"routes":["25"],"header":"Effective May 29, Stop 60607 King Edward Station @ Bay 3 is closed. Service will now use Stop 51513 located on the other side of Cambie Street.","desc":"AFFECTED\r\n25;\r\n60607 King Edward Station @ Bay 3","effect":"NO_EFFECT"},{"routes":["49"],"header":"Starting June 8, Route 49 stop changes between Wallace St and Boundary Rd will improve reliability. Alternate stops are generally within a block. New eastbound stop at 49th Ave & Wiltshire St. Check your stop before travel. More info: translink.ca/route49","desc":"Please check your usual stop before travelling, as some stops shared with Routes 41 and 26 may also be affected.","effect":"NO_EFFECT"},{"routes":["49"],"header":"Stop 51970 Eastbound E 49 Ave @ Quebec St is closed beginning Mon, Jun 15.","desc":"","effect":"NO_EFFECT"},{"routes":["49"],"header":"Stop 52036 Westbound W 49th Ave @ Laurel St is closed beginning Mon, Jun 15.","desc":"","effect":"NO_EFFECT"},{"routes":["25"],"header":"Stop 51533 Eastbound E 22nd Ave @ Lillooet St is back in service beginning Mon, Jun 15.","desc":"","effect":"NO_EFFECT"},{"routes":["99","N17"],"header":"Stop 60219 Westbound University Blvd @ Western Parkway is temporarily closed from Tue Jun 16 through Fri Jul 3 due to construction.","desc":"","effect":"REDUCED_SERVICE"},{"routes":["R4"],"header":"Stop 60548 Eastbound W 41 Avenue @ Maple Street is closed beginning Monday June 15.","desc":"","effect":"NO_EFFECT"},{"routes":["R4"],"header":"Stop 60386 Eastbound W 41 Avenue @ East Boulevard is back in service.","desc":"","effect":"NO_EFFECT"},{"routes":["33"],"header":"Stop 61093 Eastbound W 16 Ave @ East Blvd has temporarily moved 50 meters East to a pole from Fri Jun 19 through Mon Jun 22 due to construction.","desc":"","effect":"STOP_MOVED"},{"routes":["49"],"header":"Stop 52016 Westbound E 49 Ave @ Nanaimo St is temporarily closed from Fri Jun 19 to Mon Jul 6 at 3:00 PM due to construction.","desc":"","effect":"REDUCED_SERVICE"},{"routes":["49"],"header":"49 Metrotown Station trip leaving UBC Exchange @ Bay 5 at 3:36 pm is cancelled today due to operational issue.","desc":"","effect":"NO_SERVICE"},{"routes":["25"],"header":"25 Brentwood Station trip leaving UBC Exchange @ Bay 6 at 2:18 pm is cancelled today from King Edward Ave and Main St due to mechanical issue.","desc":"","effect":"NO_SERVICE"},{"routes":["25"],"header":"25 UBC trip leaving Brentwood Station @ Bay 5 at 3:53 pm is cancelled today due to mechanical issue.","desc":"","effect":"NO_SERVICE"}]}