{"generated_at":"2026-05-28T23:03:33.264409+00:00","vehicles":[{"r":"44","lat":49.28627,"lon":-123.11767,"b":null},{"r":"44","lat":49.2811,"lon":-123.12628,"b":null},{"r":"33","lat":49.25763,"lon":-123.16975,"b":null},{"r":"25","lat":49.24872,"lon":-123.16883,"b":null},{"r":"R4","lat":49.23425,"lon":-123.13802,"b":null},{"r":"99","lat":49.26688,"lon":-123.24157,"b":null},{"r":"99","lat":49.26365,"lon":-123.19781,"b":null},{"r":"R4","lat":49.23462,"lon":-123.15395,"b":null},{"r":"R4","lat":49.23407,"lon":-123.12715,"b":null},{"r":"84","lat":49.269,"lon":-123.21114,"b":null},{"r":"99","lat":49.26382,"lon":-123.20585,"b":null},{"r":"99","lat":49.2638,"lon":-123.20564,"b":null},{"r":"99","lat":49.26365,"lon":-123.19638,"b":null},{"r":"99","lat":49.26353,"lon":-123.18612,"b":null},{"r":"R4","lat":49.23462,"lon":-123.15907,"b":null},{"r":"R4","lat":49.23463,"lon":-123.16019,"b":null},{"r":"R4","lat":49.2347,"lon":-123.16998,"b":null},{"r":"44","lat":49.26817,"lon":-123.15687,"b":null},{"r":"99","lat":49.26375,"lon":-123.14468,"b":null},{"r":"99","lat":49.26377,"lon":-123.2243,"b":null},{"r":"R4","lat":49.23257,"lon":-123.06847,"b":null},{"r":"99","lat":49.262,"lon":-123.04367,"b":null},{"r":"25","lat":49.24887,"lon":-123.05665,"b":null},{"r":"R4","lat":49.23282,"lon":-123.07798,"b":null},{"r":"R4","lat":49.23278,"lon":-123.06602,"b":null},{"r":"R4","lat":49.23317,"lon":-123.10095,"b":null},{"r":"R4","lat":49.23353,"lon":-123.11794,"b":null},{"r":"99","lat":49.2624,"lon":-123.08939,"b":null},{"r":"99","lat":49.2627,"lon":-123.09663,"b":null},{"r":"99","lat":49.26345,"lon":-123.12376,"b":null},{"r":"R4","lat":49.22628,"lon":-123.12038,"b":null},{"r":"49","lat":49.22718,"lon":-123.00674,"b":null},{"r":"49","lat":49.2273,"lon":-123.00702,"b":null},{"r":"25","lat":49.26405,"lon":-123.2437,"b":null},{"r":"25","lat":49.25783,"lon":-123.18553,"b":null},{"r":"33","lat":49.25792,"lon":-123.18739,"b":null},{"r":"25","lat":49.24992,"lon":-123.17232,"b":null},{"r":"25","lat":49.24922,"lon":-123.13232,"b":null},{"r":"25","lat":49.24903,"lon":-123.12168,"b":null},{"r":"25","lat":49.2485,"lon":-123.07833,"b":null},{"r":"25","lat":49.24843,"lon":-123.07526,"b":null},{"r":"25","lat":49.25057,"lon":-123.03495,"b":null},{"r":"25","lat":49.25058,"lon":-123.04168,"b":null},{"r":"25","lat":49.24752,"lon":-123.00663,"b":null},{"r":"25","lat":49.24863,"lon":-123.084,"b":null},{"r":"25","lat":49.24912,"lon":-123.11617,"b":null},{"r":"25","lat":49.25018,"lon":-123.18505,"b":null},{"r":"33","lat":49.25848,"lon":-123.2152,"b":null},{"r":"25","lat":49.2689,"lon":-123.24775,"b":null},{"r":"R4","lat":49.23702,"lon":-123.033,"b":null},{"r":"R4","lat":49.23817,"lon":-123.03194,"b":null},{"r":"R4","lat":49.23805,"lon":-123.03205,"b":null},{"r":"R4","lat":49.23808,"lon":-123.03073,"b":null},{"r":"R4","lat":49.23775,"lon":-123.03075,"b":null},{"r":"33","lat":49.2443,"lon":-123.0456,"b":null},{"r":"R4","lat":49.23518,"lon":-123.19785,"b":null},{"r":"R4","lat":49.25428,"lon":-123.24142,"b":null},{"r":"R4","lat":49.24578,"lon":-123.23545,"b":null},{"r":"49","lat":49.23487,"lon":-123.19673,"b":null},{"r":"49","lat":49.23535,"lon":-123.19801,"b":null},{"r":"49","lat":49.2431,"lon":-123.23025,"b":null},{"r":"44","lat":49.27333,"lon":-123.23908,"b":null},{"r":"44","lat":49.26805,"lon":-123.24767,"b":null},{"r":"49","lat":49.23028,"lon":-123.18443,"b":null},{"r":"49","lat":49.22717,"lon":-123.1571,"b":null},{"r":"49","lat":49.22715,"lon":-123.15546,"b":null},{"r":"49","lat":49.22695,"lon":-123.14025,"b":null},{"r":"49","lat":49.22695,"lon":-123.14045,"b":null},{"r":"49","lat":49.2267,"lon":-123.13229,"b":null},{"r":"49","lat":49.22663,"lon":-123.1315,"b":null},{"r":"49","lat":49.22523,"lon":-123.07678,"b":null},{"r":"49","lat":49.22477,"lon":-123.05075,"b":null},{"r":"49","lat":49.22477,"lon":-123.04562,"b":null},{"r":"49","lat":49.22518,"lon":-123.06365,"b":null},{"r":"49","lat":49.22542,"lon":-123.08385,"b":null},{"r":"49","lat":49.22547,"lon":-123.08745,"b":null},{"r":"49","lat":49.22572,"lon":-123.10157,"b":null},{"r":"49","lat":49.22718,"lon":-123.15342,"b":null},{"r":"49","lat":49.22785,"lon":-123.1727,"b":null},{"r":"49","lat":49.23315,"lon":-123.18532,"b":null},{"r":"99","lat":49.26323,"lon":-123.12022,"b":null},{"r":"49","lat":49.22307,"lon":-122.99765,"b":null},{"r":"49","lat":49.22203,"lon":-123.02337,"b":null},{"r":"99","lat":49.2632,"lon":-123.06858,"b":null},{"r":"99","lat":49.26235,"lon":-123.07262,"b":null},{"r":"99","lat":49.26233,"lon":-123.07007,"b":null},{"r":"99","lat":49.26232,"lon":-123.07122,"b":null},{"r":"99","lat":49.2623,"lon":-123.07433,"b":null},{"r":"99","lat":49.26422,"lon":-123.17696,"b":null},{"r":"84","lat":49.26937,"lon":-123.10658,"b":null},{"r":"84","lat":49.268,"lon":-123.14011,"b":null},{"r":"84","lat":49.26645,"lon":-123.11504,"b":null},{"r":"44","lat":49.27323,"lon":-123.23837,"b":null},{"r":"84","lat":49.26917,"lon":-123.21574,"b":null},{"r":"33","lat":49.2552,"lon":-123.1151,"b":null},{"r":"25","lat":49.2577,"lon":-123.23035,"b":null},{"r":"33","lat":49.25845,"lon":-123.21397,"b":null},{"r":"33","lat":49.2571,"lon":-123.12442,"b":null},{"r":"33","lat":49.24062,"lon":-123.10503,"b":null},{"r":"33","lat":49.24047,"lon":-123.1027,"b":null},{"r":"99","lat":49.26333,"lon":-123.11995,"b":null},{"r":"33","lat":49.24183,"lon":-123.10783,"b":null},{"r":"99","lat":49.26412,"lon":-123.1677,"b":null},{"r":"25","lat":49.26618,"lon":-123.00246,"b":null},{"r":"25","lat":49.26628,"lon":-123.00224,"b":null},{"r":"R4","lat":49.2338,"lon":-123.1213,"b":null},{"r":"99","lat":49.26343,"lon":-123.12385,"b":null},{"r":"99","lat":49.2639,"lon":-123.15465,"b":null},{"r":"44","lat":49.27788,"lon":-123.13102,"b":null},{"r":"99","lat":49.26362,"lon":-123.14305,"b":null},{"r":"99","lat":49.26363,"lon":-123.14215,"b":null},{"r":"99","lat":49.26378,"lon":-123.15488,"b":null},{"r":"49","lat":49.2515,"lon":-123.23315,"b":null},{"r":"49","lat":49.25915,"lon":-123.23923,"b":null},{"r":"25","lat":49.26447,"lon":-123.00287,"b":null},{"r":"68","lat":49.26058,"lon":-123.25263,"b":null},{"r":"68","lat":49.25633,"lon":-123.24263,"b":null},{"r":"99","lat":49.26653,"lon":-123.24565,"b":null},{"r":"99","lat":49.26745,"lon":-123.24688,"b":null},{"r":"68","lat":49.26837,"lon":-123.24858,"b":null},{"r":"84","lat":49.267,"lon":-123.24848,"b":null},{"r":"R4","lat":49.2668,"lon":-123.24593,"b":null},{"r":"R4","lat":49.26707,"lon":-123.24797,"b":null},{"r":"49","lat":49.2666,"lon":-123.24578,"b":null},{"r":"49","lat":49.26782,"lon":-123.24744,"b":null},{"r":"44","lat":49.28557,"lon":-123.11929,"b":null},{"r":"49","lat":49.22625,"lon":-123.00428,"b":null},{"r":"49","lat":49.22623,"lon":-123.00453,"b":null},{"r":"99","lat":49.26815,"lon":-123.2479,"b":null},{"r":"R4","lat":49.23322,"lon":-123.10854,"b":null},{"r":"R4","lat":49.23377,"lon":-123.12472,"b":null},{"r":"R4","lat":49.2333,"lon":-123.11097,"b":null},{"r":"R4","lat":49.23477,"lon":-123.18415,"b":null},{"r":"R4","lat":49.23465,"lon":-123.15443,"b":null},{"r":"R4","lat":49.23465,"lon":-123.15482,"b":null},{"r":"R4","lat":49.26882,"lon":-123.24754,"b":null},{"r":"R4","lat":49.26792,"lon":-123.2478,"b":null},{"r":"R4","lat":49.26248,"lon":-123.2422,"b":null},{"r":"R4","lat":49.26265,"lon":-123.24232,"b":null},{"r":"99","lat":49.26345,"lon":-123.12688,"b":null},{"r":"99","lat":49.26342,"lon":-123.12727,"b":null},{"r":"84","lat":49.26807,"lon":-123.14945,"b":null},{"r":"84","lat":49.266,"lon":-123.12795,"b":null},{"r":"99","lat":49.26305,"lon":-123.10487,"b":null},{"r":"99","lat":49.26333,"lon":-123.1157,"b":null},{"r":"99","lat":49.26308,"lon":-123.1046,"b":null},{"r":"25","lat":49.24315,"lon":-123.06075,"b":null},{"r":"99","lat":49.2629,"lon":-123.09773,"b":null}],"alerts":[{"routes":["R4"],"header":"Stop 60386 Eastbound W 41 Ave @ East Blvd is temporarily closed beginning Monday May 4. Please use new stop 60548 near Maple St.","desc":"","effect":"NO_EFFECT"},{"routes":["49"],"header":"UPDATE: Stop 51987 Eastbound E 49 Ave @ Elliott St is temporarily closed from Tue May 12 through Mon Jun 1 due to construction. 430 bus will be picking up passengers at the next stop #51988 EB 49 Ave and Vivian St.","desc":"","effect":"REDUCED_SERVICE"},{"routes":["84"],"header":"Stop 59758 Eastbound W 2nd Ave @ Columbia St is temporarily closed from Wed May 20 through Sat May 30 due to construction.","desc":"","effect":"REDUCED_SERVICE"},{"routes":["49"],"header":"Stop 60732 Westbound 49 Ave @ Main St is closed beginning Monday May 18. Please use original stop 52030 on other side of Main St.","desc":"","effect":"NO_EFFECT"},{"routes":["25"],"header":"Stop 51542 Northbound Willingdon Ave @ Goard Way is temporarily closed from Tue May 26 through Tue Jun 9 due to construction.","desc":"222 service will use stop 51543 at Northbound Willingdon Ave at Canada Way.","effect":"REDUCED_SERVICE"},{"routes":["99"],"header":"Effective May 20, 99 UBC B-Line detour at Broadway & Main Street has ended. Service is now back to regular route along Broadway.","desc":"","effect":"DETOUR"},{"routes":["49"],"header":"UPDATE: Stop 59434 Westbound E 49 Ave @ Vivian St is temporarily closed from Wed May 20 through Mon Jun 1 due to construction.","desc":"","effect":"REDUCED_SERVICE"},{"routes":["R4"],"header":"R4 41st Ave to Joyce Station/41st Ave to UBC service is experiencing delays in both directions as of 2:15 PM due to traffic.","desc":"","effect":"SIGNIFICANT_DELAYS"},{"routes":["44"],"header":"44 UBC trip leaving Waterfront Station @ Bay 1 at 2:58 pm is cancelled today due to mechanical issue.","desc":"","effect":"NO_SERVICE"},{"routes":["R4"],"header":"R4 41st Ave to UBC trip leaving Joyce Station @ Bay 4 at 2:54 pm is cancelled today due to motor vehicle accident.","desc":"","effect":"NO_SERVICE"},{"routes":["33"],"header":"33 UBC trip leaving 29th Avenue Station @ Bay 1 at 2:51 pm is cancelled today from 33 Ave and Argyle St due to mechanical issue.","desc":"","effect":"NO_SERVICE"},{"routes":["33"],"header":"33 29th Ave Station trip leaving UBC Exchange @ Bay 1 at 4:01 pm is cancelled today due to traffic. Resume from W 16 Ave and Wesbrook Mall.","desc":"","effect":"NO_SERVICE"},{"routes":["49"],"header":"49 Metrotown Station trip leaving UBC Exchange @ Bay 5 at 2:45 pm is cancelled today from E 49 Ave and Windsor St due to traffic.","desc":"","effect":"NO_SERVICE"},{"routes":["33"],"header":"33 UBC trip leaving 29th Avenue Station @ Bay 1 at 3:17 pm is cancelled today from W 16 Ave and Pacific Spirit Park due to traffic.","desc":"","effect":"NO_SERVICE"},{"routes":["R4"],"header":"R4 41st Ave to Joyce Station trip leaving UBC Exchange @ Bay 4 at 3:50 pm is cancelled today due to motor vehicle accident. Resume at W 41 Ave and Oak St","desc":"","effect":"NO_SERVICE"}]}