{"generated_at":"2026-05-24T18:48:18.474580+00:00","vehicles":[{"r":"99","lat":49.26365,"lon":-123.19748,"b":null},{"r":"25","lat":49.2567,"lon":-123.18505,"b":null},{"r":"99","lat":49.2639,"lon":-123.1579,"b":null},{"r":"99","lat":49.26352,"lon":-123.18616,"b":null},{"r":"25","lat":49.25667,"lon":-123.18523,"b":null},{"r":"R4","lat":49.23462,"lon":-123.15681,"b":null},{"r":"84","lat":49.26788,"lon":-123.13982,"b":null},{"r":"99","lat":49.26378,"lon":-123.15276,"b":null},{"r":"R4","lat":49.23282,"lon":-123.0765,"b":null},{"r":"R4","lat":49.23922,"lon":-123.031,"b":null},{"r":"25","lat":49.24893,"lon":-123.11708,"b":null},{"r":"25","lat":49.24845,"lon":-123.07532,"b":null},{"r":"25","lat":49.2506,"lon":-123.04332,"b":null},{"r":"25","lat":49.24888,"lon":-123.0152,"b":null},{"r":"25","lat":49.2492,"lon":-123.12082,"b":null},{"r":"49","lat":49.26275,"lon":-123.2424,"b":null},{"r":"25","lat":49.26838,"lon":-123.24799,"b":null},{"r":"49","lat":49.26815,"lon":-123.24802,"b":null},{"r":"49","lat":49.22295,"lon":-123.02772,"b":null},{"r":"R4","lat":49.238,"lon":-123.03125,"b":null},{"r":"33","lat":49.24428,"lon":-123.0456,"b":null},{"r":"R4","lat":49.23852,"lon":-123.21062,"b":null},{"r":"R4","lat":49.24527,"lon":-123.23403,"b":null},{"r":"84","lat":49.2689,"lon":-123.2475,"b":null},{"r":"49","lat":49.22718,"lon":-123.15552,"b":null},{"r":"49","lat":49.22548,"lon":-123.08992,"b":null},{"r":"49","lat":49.22212,"lon":-123.01252,"b":null},{"r":"49","lat":49.22478,"lon":-123.04185,"b":null},{"r":"99","lat":49.2633,"lon":-123.06882,"b":null},{"r":"68","lat":49.26785,"lon":-123.24785,"b":null},{"r":"99","lat":49.26247,"lon":-123.08815,"b":null},{"r":"33","lat":49.2571,"lon":-123.12479,"b":null},{"r":"99","lat":49.2633,"lon":-123.11657,"b":null},{"r":"25","lat":49.26632,"lon":-123.00173,"b":null},{"r":"33","lat":49.25705,"lon":-123.12147,"b":null},{"r":"99","lat":49.26318,"lon":-123.11217,"b":null},{"r":"99","lat":49.26242,"lon":-123.06873,"b":null},{"r":"84","lat":49.26912,"lon":-123.10049,"b":null},{"r":"68","lat":49.26037,"lon":-123.25232,"b":null},{"r":"99","lat":49.2678,"lon":-123.24741,"b":null},{"r":"R4","lat":49.23282,"lon":-123.09068,"b":null},{"r":"33","lat":49.26802,"lon":-123.24813,"b":null},{"r":"99","lat":49.26823,"lon":-123.24805,"b":null},{"r":"49","lat":49.23482,"lon":-123.18645,"b":null},{"r":"R4","lat":49.23465,"lon":-123.1548,"b":null},{"r":"R4","lat":49.26868,"lon":-123.24735,"b":null},{"r":"99","lat":49.26307,"lon":-123.10461,"b":null},{"r":"25","lat":49.24358,"lon":-123.0617,"b":null},{"r":"49","lat":49.22602,"lon":-123.1129,"b":null}],"alerts":[{"routes":["R4"],"header":"Stop 60386 Eastbound W 41 Ave @ East Blvd is temporarily closed beginning Monday May 4. Please use new stop 60548 near Maple St.","desc":"","effect":"NO_EFFECT"},{"routes":["49"],"header":"UPDATE: Stop 51987 Eastbound E 49 Ave @ Elliott St is temporarily closed from Tue May 12 through Fri May 29 due to construction. 430 bus will be picking up passengers at the next stop #51988 EB 49 Ave and Vivian St.","desc":"","effect":"REDUCED_SERVICE"},{"routes":["84"],"header":"Stop 59758 Eastbound W 2nd Ave @ Columbia St is temporarily closed from Wed May 20 through Sat May 30 due to construction.","desc":"","effect":"REDUCED_SERVICE"},{"routes":["49"],"header":"Stop 60732 Westbound 49 Ave @ Main St is closed beginning Monday May 18. Please use original stop 52030 on other side of Main St.","desc":"","effect":"NO_EFFECT"},{"routes":["R4"],"header":"R4 41st Ave to Joyce Station detour Sun May 24 from 6:00 AM to 8:00 PM. Regular route to 41 Ave & Rupert, then Rupert, Willington Ave, Joyce then resume regular route due to construction. Servicing Stop at Rupert St & Kingsway #51670","desc":"Temporary Stop: \r\nRupert St & Kingsway \r\n\nAffected stops:\r\n51128 Eastbound E 41 Ave @ Rupert St\r\n51636 Northbound Joyce St @ Kingsway","effect":"DETOUR"},{"routes":["R4"],"header":"R4 41st Ave to UBC detour from Sun May 24 from 6:00 AM to 8:00 PM. From terminus to Joyce St, Wellington Ave, Rupert St, then resume regular route due to construction. Serving stop at Rupert & Kingsway #51604","desc":"Affected stops:\r\n51178 Southbound Joyce St @ Kingsway\r\n51181 Westbound E 41 Ave @ Rupert St","effect":"DETOUR"},{"routes":["49"],"header":"Stop 52015 Westbound E 49 Ave @ Elliott St is temporarily closed from Wed May 20 to Tue May 26 from 7:00 AM to 3:00 PM daily due to construction. 430 bus will be picking up passengers at the next stop 52016 WB 49 Ave and Nanaimo St.","desc":"","effect":"REDUCED_SERVICE"},{"routes":["49"],"header":"UPDATE: Stop 59434 Westbound E 49 Ave @ Vivian St is temporarily closed from Wed May 20 through Fri May 29 due to construction.","desc":"","effect":"REDUCED_SERVICE"},{"routes":["99"],"header":"Effective May 20, 99 UBC B-Line detour at Broadway & Main Street has ended. Service is now back to regular route along Broadway.","desc":"","effect":"DETOUR"},{"routes":["25"],"header":"Stop 51556 Westbound E 22 Ave @ Windermere St is temporarily closed from Thu May 21 through Tue May 26 due to construction.","desc":"","effect":"REDUCED_SERVICE"},{"routes":["99"],"header":"99 UBC B-Line trip leaving Commercial-Broadway Station @ Bay 5 at 10:07 am is cancelled today due to on-board incident from Broadway-City Hall.","desc":"","effect":"NO_SERVICE"},{"routes":["99"],"header":"Update - trip reinstated. 99 Commercial-Broadway Station B-Line trip leaving UBC Exchange @ Bay 7 at 10:55 am is cancelled today due to on-board incident.","desc":"","effect":"NO_SERVICE"}]}