{"generated_at":"2026-06-27T22:47:16.950784+00:00","vehicles":[{"r":"99","lat":49.26377,"lon":-123.22027,"b":null},{"r":"R4","lat":49.23467,"lon":-123.15438,"b":null},{"r":"99","lat":49.26382,"lon":-123.1554,"b":null},{"r":"84","lat":49.26872,"lon":-123.1966,"b":null},{"r":"R4","lat":49.23463,"lon":-123.15892,"b":null},{"r":"99","lat":49.26377,"lon":-123.14547,"b":null},{"r":"84","lat":49.26822,"lon":-123.15553,"b":null},{"r":"R4","lat":49.23385,"lon":-123.12695,"b":null},{"r":"99","lat":49.26283,"lon":-123.09983,"b":null},{"r":"99","lat":49.26355,"lon":-123.13644,"b":null},{"r":"R4","lat":49.23292,"lon":-123.05835,"b":null},{"r":"R4","lat":49.23282,"lon":-123.05779,"b":null},{"r":"25","lat":49.24712,"lon":-123.06948,"b":null},{"r":"49","lat":49.22637,"lon":-123.00467,"b":null},{"r":"25","lat":49.25808,"lon":-123.19945,"b":null},{"r":"25","lat":49.2504,"lon":-123.15083,"b":null},{"r":"25","lat":49.2487,"lon":-123.10059,"b":null},{"r":"25","lat":49.25057,"lon":-123.0433,"b":null},{"r":"25","lat":49.25065,"lon":-123.02872,"b":null},{"r":"25","lat":49.24242,"lon":-123.05765,"b":null},{"r":"25","lat":49.24862,"lon":-123.0846,"b":null},{"r":"25","lat":49.2495,"lon":-123.13797,"b":null},{"r":"25","lat":49.25827,"lon":-123.20413,"b":null},{"r":"25","lat":49.2689,"lon":-123.24762,"b":null},{"r":"33","lat":49.26835,"lon":-123.24809,"b":null},{"r":"49","lat":49.26822,"lon":-123.24807,"b":null},{"r":"R4","lat":49.2371,"lon":-123.03297,"b":null},{"r":"49","lat":49.22295,"lon":-123.02768,"b":null},{"r":"R4","lat":49.23788,"lon":-123.03101,"b":null},{"r":"33","lat":49.24428,"lon":-123.04559,"b":null},{"r":"R4","lat":49.2363,"lon":-123.20193,"b":null},{"r":"49","lat":49.23475,"lon":-123.18615,"b":null},{"r":"R4","lat":49.23482,"lon":-123.18642,"b":null},{"r":"49","lat":49.2352,"lon":-123.19753,"b":null},{"r":"84","lat":49.2686,"lon":-123.24797,"b":null},{"r":"49","lat":49.22567,"lon":-123.10204,"b":null},{"r":"49","lat":49.22523,"lon":-123.0711,"b":null},{"r":"49","lat":49.222,"lon":-123.00945,"b":null},{"r":"49","lat":49.2251,"lon":-123.05952,"b":null},{"r":"49","lat":49.22545,"lon":-123.08791,"b":null},{"r":"49","lat":49.22582,"lon":-123.1067,"b":null},{"r":"49","lat":49.22987,"lon":-123.17783,"b":null},{"r":"99","lat":49.2632,"lon":-123.1163,"b":null},{"r":"99","lat":49.26287,"lon":-123.06773,"b":null},{"r":"99","lat":49.26322,"lon":-123.06857,"b":null},{"r":"99","lat":49.2633,"lon":-123.06882,"b":null},{"r":"99","lat":49.26338,"lon":-123.06908,"b":null},{"r":"99","lat":49.2625,"lon":-123.06968,"b":null},{"r":"99","lat":49.26418,"lon":-123.17348,"b":null},{"r":"84","lat":49.26587,"lon":-123.1168,"b":null},{"r":"84","lat":49.26553,"lon":-123.08128,"b":null},{"r":"68","lat":49.26792,"lon":-123.24783,"b":null},{"r":"33","lat":49.24015,"lon":-123.07097,"b":null},{"r":"33","lat":49.257,"lon":-123.11925,"b":null},{"r":"33","lat":49.25732,"lon":-123.13799,"b":null},{"r":"99","lat":49.26327,"lon":-123.12177,"b":null},{"r":"99","lat":49.26438,"lon":-123.18559,"b":null},{"r":"25","lat":49.2662,"lon":-123.00207,"b":null},{"r":"R4","lat":49.2337,"lon":-123.11755,"b":null},{"r":"99","lat":49.264,"lon":-123.16122,"b":null},{"r":"99","lat":49.26373,"lon":-123.1515,"b":null},{"r":"49","lat":49.25122,"lon":-123.23296,"b":null},{"r":"84","lat":49.26688,"lon":-123.09499,"b":null},{"r":"25","lat":49.26625,"lon":-123.0016,"b":null},{"r":"25","lat":49.26447,"lon":-123.00288,"b":null},{"r":"68","lat":49.25873,"lon":-123.24467,"b":null},{"r":"R4","lat":49.23272,"lon":-123.08038,"b":null},{"r":"49","lat":49.22623,"lon":-123.00436,"b":null},{"r":"99","lat":49.2688,"lon":-123.24741,"b":null},{"r":"99","lat":49.26835,"lon":-123.24815,"b":null},{"r":"R4","lat":49.25827,"lon":-123.23867,"b":null},{"r":"R4","lat":49.26875,"lon":-123.24748,"b":null},{"r":"R4","lat":49.2683,"lon":-123.24809,"b":null},{"r":"49","lat":49.22625,"lon":-123.12068,"b":null},{"r":"99","lat":49.26287,"lon":-123.09785,"b":null},{"r":"68","lat":49.26017,"lon":-123.25397,"b":null}],"alerts":[{"routes":["49"],"header":"Stop 51969 Eastbound W 49 Ave @ Manitoba St  is back in service beginning Mon, Jun 1.","desc":"","effect":"NO_EFFECT"},{"routes":["49"],"header":"Stop Westbound W 49 Ave @ Cambie St is closed beginning Mon, Jun 1. Please use new stop 61218 Langara-49th Station @ Bay 2, on other side of Cambie St.","desc":"","effect":"NO_EFFECT"},{"routes":["49"],"header":"Stop 62043 Westbound E 49 Ave @ Quebec St is temporarily closed beginning Mon, Jun 1.","desc":"","effect":"NO_EFFECT"},{"routes":["49"],"header":"The following Eastbound stops for Bus 49 Metrotown  are closed beginning Monday June 8.","desc":"Stop 51890 Eastbound W 41 Avenue @ Highbury Street is closed beginning Monday June 8.\r\nStop 51944 Southbound Dunbar Street @ W 43 Avenue is closed beginning Monday June 8.\r\nStop 51952 Eastbound W 49 Avenue @ Balsam Street is closed beginning Monday June 8.\r\nStop 51955 Eastbound W 49 Avenue @ East Blvd Street is closed beginning Monday June 8.\r\nStop 51957 Eastbound W 49 Avenue @ Angus Drive is clos","effect":"NO_EFFECT"},{"routes":["33"],"header":"Stop 51817 Eastbound E 29 Ave @ Slocan St is temporarily closed beginning Monday June 8.","desc":"","effect":"NO_EFFECT"},{"routes":["49"],"header":"The following stops for bus 49 Westbound are closed beginning Monday June 8.","desc":"Stop 51894 Westbound W 41 Avenue @ Olympic Street is closed beginning Monday June 8.\r\nStop 52054 Northbound Dunbar Street @  W 43 Avenue is closed beginning Monday June 8.\r\nStop 52042 Westbound W 49 Avenue @ Adera Street is closed beginning Monday June 8.\r\nStop 52024 Westbound E 49 Avenue @ Ross Street is closed beginning Monday June 8.\r\nStop 52019 Westbound E 49 Avenue @ Beatrice Street is closed","effect":"NO_EFFECT"},{"routes":["49"],"header":"Starting June 8, Route 49 stop changes between Wallace St and Boundary Rd will improve reliability. Alternate stops are generally within a block. New eastbound stop at 49th Ave & Wiltshire St. Check your stop before travel. More info: translink.ca/route49","desc":"Please check your usual stop before travelling, as some stops shared with Routes 41 and 26 may also be affected.","effect":"NO_EFFECT"},{"routes":["49"],"header":"Stop 51970 Eastbound E 49 Ave @ Quebec St is closed beginning Mon, Jun 15.","desc":"","effect":"NO_EFFECT"},{"routes":["49"],"header":"Stop 52036 Westbound W 49th Ave @ Laurel St is closed beginning Mon, Jun 15.","desc":"","effect":"NO_EFFECT"},{"routes":["25"],"header":"Stop 51533 Eastbound E 22nd Ave @ Lillooet St is back in service beginning Mon, Jun 15.","desc":"","effect":"NO_EFFECT"},{"routes":["R4"],"header":"Stop 60548 Eastbound W 41 Avenue @ Maple Street is closed beginning Monday June 15.","desc":"","effect":"NO_EFFECT"},{"routes":["R4"],"header":"Stop 60386 Eastbound W 41 Avenue @ East Boulevard is back in service.","desc":"","effect":"NO_EFFECT"},{"routes":["49"],"header":"UPDATE: Stop 52015 Westbound E 49 Ave @ Elliott St has temporarily moved 60 metres east to the other side of Elliott St from Mon Jun 22 through Mon Jul 6 due to construction.","desc":"","effect":"STOP_MOVED"},{"routes":["49"],"header":"Stop 52016 Westbound E 49 Ave @ Nanaimo St is temporarily closed from Fri Jun 19 to Mon Jul 6 at 3:00 PM due to construction.","desc":"","effect":"REDUCED_SERVICE"},{"routes":["N17"],"header":"Stop 50572 Westbound W 10 Ave @ Crown St is temporarily closed from Thu Jun 25 due to construction","desc":"","effect":"NO_EFFECT"},{"routes":["25"],"header":"25 UBC trip leaving Brentwood Station @ Bay 5 at 1:42 pm is cancelled today from Wesbrook Mall and 2900 Block due to traffic.","desc":"","effect":"NO_SERVICE"},{"routes":["25"],"header":"25 Brentwood Station trip leaving UBC Exchange @ Bay 6 at 3:12 pm is cancelled today due to traffic. Resume at W 16 Ave and Wesbrook Mall","desc":"","effect":"NO_SERVICE"}]}