{"generated_at":"2026-07-07T21:06:22.489771+00:00","vehicles":[{"r":"44","lat":49.28555,"lon":-123.11608,"b":null},{"r":"R4","lat":49.23438,"lon":-123.1391,"b":null},{"r":"R4","lat":49.23423,"lon":-123.13813,"b":null},{"r":"99","lat":49.26692,"lon":-123.2415,"b":null},{"r":"44","lat":49.26893,"lon":-123.20638,"b":null},{"r":"84","lat":49.26902,"lon":-123.21153,"b":null},{"r":"84","lat":49.26785,"lon":-123.14014,"b":null},{"r":"99","lat":49.26393,"lon":-123.21805,"b":null},{"r":"84","lat":49.26808,"lon":-123.14653,"b":null},{"r":"44","lat":49.2686,"lon":-123.18182,"b":null},{"r":"25","lat":49.2439,"lon":-123.06237,"b":null},{"r":"R4","lat":49.23388,"lon":-123.12665,"b":null},{"r":"99","lat":49.26322,"lon":-123.11407,"b":null},{"r":"99","lat":49.26258,"lon":-123.08994,"b":null},{"r":"99","lat":49.26352,"lon":-123.13721,"b":null},{"r":"R4","lat":49.23277,"lon":-123.04958,"b":null},{"r":"49","lat":49.26183,"lon":-123.24181,"b":null},{"r":"33","lat":49.25805,"lon":-123.19736,"b":null},{"r":"25","lat":49.25797,"lon":-123.19252,"b":null},{"r":"25","lat":49.2494,"lon":-123.14407,"b":null},{"r":"25","lat":49.24885,"lon":-123.11073,"b":null},{"r":"25","lat":49.24857,"lon":-123.0836,"b":null},{"r":"25","lat":49.25058,"lon":-123.03304,"b":null},{"r":"25","lat":49.24885,"lon":-123.0234,"b":null},{"r":"25","lat":49.24872,"lon":-123.09063,"b":null},{"r":"33","lat":49.26872,"lon":-123.24838,"b":null},{"r":"49","lat":49.26898,"lon":-123.2481,"b":null},{"r":"R4","lat":49.23852,"lon":-123.03233,"b":null},{"r":"R4","lat":49.23792,"lon":-123.03098,"b":null},{"r":"33","lat":49.2443,"lon":-123.0456,"b":null},{"r":"R4","lat":49.23855,"lon":-123.21104,"b":null},{"r":"49","lat":49.23702,"lon":-123.2047,"b":null},{"r":"49","lat":49.23438,"lon":-123.18542,"b":null},{"r":"R4","lat":49.23482,"lon":-123.1864,"b":null},{"r":"84","lat":49.2694,"lon":-123.2476,"b":null},{"r":"49","lat":49.22715,"lon":-123.15536,"b":null},{"r":"49","lat":49.22678,"lon":-123.13409,"b":null},{"r":"49","lat":49.22597,"lon":-123.1125,"b":null},{"r":"49","lat":49.226,"lon":-123.11224,"b":null},{"r":"49","lat":49.22597,"lon":-123.11279,"b":null},{"r":"49","lat":49.22498,"lon":-123.05853,"b":null},{"r":"49","lat":49.2257,"lon":-123.00954,"b":null},{"r":"49","lat":49.22692,"lon":-123.0082,"b":null},{"r":"49","lat":49.22198,"lon":-123.00965,"b":null},{"r":"49","lat":49.22478,"lon":-123.0419,"b":null},{"r":"49","lat":49.22523,"lon":-123.06755,"b":null},{"r":"49","lat":49.22572,"lon":-123.10236,"b":null},{"r":"49","lat":49.22662,"lon":-123.12801,"b":null},{"r":"49","lat":49.22635,"lon":-123.12172,"b":null},{"r":"49","lat":49.22673,"lon":-123.13302,"b":null},{"r":"99","lat":49.26292,"lon":-123.02945,"b":null},{"r":"99","lat":49.26322,"lon":-123.06855,"b":null},{"r":"99","lat":49.26418,"lon":-123.17613,"b":null},{"r":"84","lat":49.26928,"lon":-123.10132,"b":null},{"r":"84","lat":49.26603,"lon":-123.0813,"b":null},{"r":"68","lat":49.25793,"lon":-123.25018,"b":null},{"r":"68","lat":49.26762,"lon":-123.2475,"b":null},{"r":"99","lat":49.26257,"lon":-123.09512,"b":null},{"r":"99","lat":49.26233,"lon":-123.07902,"b":null},{"r":"25","lat":49.26133,"lon":-123.24117,"b":null},{"r":"33","lat":49.25708,"lon":-123.12748,"b":null},{"r":"33","lat":49.257,"lon":-123.1192,"b":null},{"r":"33","lat":49.2572,"lon":-123.12685,"b":null},{"r":"99","lat":49.26337,"lon":-123.12145,"b":null},{"r":"99","lat":49.2641,"lon":-123.16762,"b":null},{"r":"R4","lat":49.23372,"lon":-123.11782,"b":null},{"r":"99","lat":49.26318,"lon":-123.11201,"b":null},{"r":"99","lat":49.2639,"lon":-123.1547,"b":null},{"r":"33","lat":49.24047,"lon":-123.10163,"b":null},{"r":"99","lat":49.26247,"lon":-123.0761,"b":null},{"r":"99","lat":49.26242,"lon":-123.06873,"b":null},{"r":"99","lat":49.26368,"lon":-123.14855,"b":null},{"r":"49","lat":49.2527,"lon":-123.23389,"b":null},{"r":"25","lat":49.26445,"lon":-123.00293,"b":null},{"r":"25","lat":49.26623,"lon":-123.00179,"b":null},{"r":"68","lat":49.25973,"lon":-123.24692,"b":null},{"r":"99","lat":49.26652,"lon":-123.24572,"b":null},{"r":"R4","lat":49.23275,"lon":-123.08338,"b":null},{"r":"33","lat":49.26815,"lon":-123.24812,"b":null},{"r":"R4","lat":49.26465,"lon":-123.24419,"b":null},{"r":"R4","lat":49.26792,"lon":-123.2474,"b":null},{"r":"25","lat":49.26722,"lon":-123.2478,"b":null},{"r":"25","lat":49.26803,"lon":-123.24837,"b":null},{"r":"49","lat":49.22617,"lon":-123.00432,"b":null},{"r":"49","lat":49.22607,"lon":-123.00412,"b":null},{"r":"99","lat":49.26818,"lon":-123.24776,"b":null},{"r":"25","lat":49.24833,"lon":-123.05653,"b":null},{"r":"R4","lat":49.23475,"lon":-123.18412,"b":null},{"r":"R4","lat":49.25532,"lon":-123.23783,"b":null},{"r":"R4","lat":49.26432,"lon":-123.24377,"b":null},{"r":"99","lat":49.26348,"lon":-123.13893,"b":null},{"r":"99","lat":49.26328,"lon":-123.11398,"b":null},{"r":"99","lat":49.26325,"lon":-123.11145,"b":null},{"r":"25","lat":49.25017,"lon":-123.17903,"b":null},{"r":"33","lat":49.24025,"lon":-123.07725,"b":null}],"alerts":[{"routes":["33"],"header":"Stop 61101 Eastbound E 33 Ave @ Ontario St is temporarily closed from Thu Jun 11 to Fri Jul 10, 7:00 AM to 3:00 PM daily (except Sundays), due to construction.","desc":"","effect":"REDUCED_SERVICE"},{"routes":["49"],"header":"Starting June 8, Route 49 stop changes between Wallace St and Boundary Rd will improve reliability. Alternate stops are generally within a block. New eastbound stop at 49th Ave & Wiltshire St. Check your stop before travel. More info: translink.ca/route49","desc":"Please check your usual stop before travelling, as some stops shared with Routes 41 and 26 may also be affected.","effect":"NO_EFFECT"},{"routes":["49"],"header":"Stop 51970 Eastbound E 49 Ave @ Quebec St is closed beginning Mon, Jun 15.","desc":"","effect":"NO_EFFECT"},{"routes":["49"],"header":"Stop 52036 Westbound W 49th Ave @ Laurel St is closed beginning Mon, Jun 15.","desc":"","effect":"NO_EFFECT"},{"routes":["R4"],"header":"Stop 60548 Eastbound W 41 Avenue @ Maple Street is closed beginning Monday June 15.","desc":"","effect":"NO_EFFECT"},{"routes":["N17"],"header":"Stop 50572 Westbound W 10 Ave @ Crown St is temporarily closed from Thu Jun 25 due to construction","desc":"","effect":"NO_EFFECT"},{"routes":["99","N17"],"header":"UPDATE: Stop 60219 Westbound University Blvd @ Western Parkway is temporarily closed through Fri Jul 17 due to construction.","desc":"","effect":"REDUCED_SERVICE"},{"routes":["25"],"header":"Stop 51564 Westbound E King Edward Ave @ Knight St is temporarily closed on Tue Jul 7 from 9:30 AM to 2:30 PM due to construction.","desc":"","effect":"REDUCED_SERVICE"},{"routes":["25"],"header":"Stop 51566 Westbound E King Edward Ave @ Windsor St is temporarily closed on Tue Jul 7 from 9:30 AM to 2:30 PM due to construction.","desc":"","effect":"REDUCED_SERVICE"},{"routes":["R4"],"header":"R4 41st Ave to Joyce Station trip leaving UBC Exchange @ Bay 4 at 1:02 pm is cancelled today due to mechanical issue.","desc":"","effect":"NO_SERVICE"},{"routes":["49"],"header":"UPDATE 1:35 PM: 49 UBC trip leaving Metrotown Station @ Bay 11 at 12:47 pm is cancelled today due to mechanical issue. Resume from Dunbar Loop.","desc":"","effect":"NO_SERVICE"},{"routes":["R4"],"header":"UPDATE 1:00 PM: R4 41st Ave to UBC trip leaving Joyce Station @ Bay 4 at 12:37 pm is cancelled today due to mechanical issue. Resume from W 41 Ave and Oak St.","desc":"","effect":"NO_SERVICE"},{"routes":["R4"],"header":"R4 41st Ave to UBC trip leaving Joyce Station @ Bay 4 at 1:57 pm is cancelled today due to mechanical issue.","desc":"","effect":"NO_SERVICE"}]}